EGAIN/__init__.py
egain-0.0.1.dist-info/licenses/LICENSE.txt
egain-0.0.1.dist-info/METADATA
egain-0.0.1.dist-info/WHEEL
egain-0.0.1.dist-info/top_level.txt
egain-0.0.1.dist-info/RECORD
