Metadata-Version: 2.4
Name: EGAIN
Version: 0.0.1
Summary: Enhanced Generative Adversarial Networks for Imputing Missing Values
Author-email: Abolfazl Saghafi <asaghafi@sju.edu>
Project-URL: Homepage, https://github.com/asaghafi/EGAIN
Project-URL: Issues, https://github.com/asaghafi/EGAIN
Classifier: Programming Language :: Python :: 3
Classifier: Operating System :: OS Independent
Classifier: License :: OSI Approved :: Apache Software License
Requires-Python: >=3.11
License-File: LICENSE.txt
Dynamic: license-file
